pyicu_slugify/__init__.py
pyicu_slugify/slugify.py
pyicu_slugify-0.1.1.dist-info/LICENSE
pyicu_slugify-0.1.1.dist-info/METADATA
pyicu_slugify-0.1.1.dist-info/WHEEL
pyicu_slugify-0.1.1.dist-info/top_level.txt
pyicu_slugify-0.1.1.dist-info/RECORD
