Metadata-Version: 2.1
Name: pyicu-slugify
Version: 0.1.1
Summary: A CLDR-compliant slugify function using PyICU
Author: Miguel Pachas García
Author-email: miguel.pachas.garcia@gmail.com
License: MIT
Classifier: License :: OSI Approved :: MIT License
Classifier: Programming Language :: Python :: 3
Classifier: Programming Language :: Python :: 3.7
Classifier: Programming Language :: Python :: 3.8
Classifier: Programming Language :: Python :: 3.9
Classifier: Programming Language :: Python :: 3.10
Classifier: Programming Language :: Python :: 3.11
Classifier: Programming Language :: Python :: 3.12
Requires-Python: >=3.7
License-File: LICENSE
Requires-Dist: PyICU >=2.8
